{
	"format_version": "1.8.0",
	"animations": {
		"animation.model.idle": {
			"animation_length": 1.5,
			"bones": {
				"neak": {
					"rotation": {
						"0.0": {
							"vector": [0, 0, 0]
						},
						"0.7083": {
							"vector": [0, 0, 0]
						},
						"1.5": {
							"vector": [0, 0, 0]
						}
					},
					"position": {
						"0.0": {
							"vector": [0, 0, 0]
						},
						"0.7083": {
							"vector": [0, 0, -1]
						},
						"1.5": {
							"vector": [0, 0, 0]
						}
					}
				},
				"head": {
					"rotation": {
						"0.0": {
							"vector": [0, 0, 0]
						},
						"0.7083": {
							"vector": [-2.5, 0, 0]
						},
						"1.5": {
							"vector": [0, 0, 0]
						}
					},
					"position": {
						"0.0": {
							"vector": [0, 0, 0]
						},
						"0.7083": {
							"vector": [0, 0, -1]
						},
						"1.5": {
							"vector": [0, 0, 0]
						}
					}
				},
				"Lwing": {
					"rotation": {
						"0.0": {
							"vector": [0, 0, 0]
						},
						"0.7083": {
							"vector": [2.5, 0, 0]
						},
						"1.5": {
							"vector": [0, 0, 0]
						}
					},
					"position": {
						"0.0": {
							"vector": [0, 0, 0]
						},
						"1.5": {
							"vector": [0, 0, 0]
						}
					}
				},
				"Rwing": {
					"rotation": {
						"0.0": {
							"vector": [0, 0, 0]
						},
						"0.7083": {
							"vector": [2.5, 0, 0]
						},
						"1.5": {
							"vector": [0, 0, 0]
						}
					},
					"position": {
						"0.0": {
							"vector": [0, 0, 0]
						},
						"1.5": {
							"vector": [0, 0, 0]
						}
					}
				},
				"body": {
					"rotation": {
						"0.0": {
							"vector": [2.5, 0, 0]
						},
						"0.7083": {
							"vector": [5, 0, 0]
						},
						"1.5": {
							"vector": [2.5, 0, 0]
						}
					},
					"position": {
						"0.0": {
							"vector": [0, 0, 0]
						},
						"1.5": {
							"vector": [0, 0, 0]
						}
					}
				}
			}
		},
		"animation.model.fly": {
			"animation_length": 0.375,
			"bones": {
				"Lwing": {
					"rotation": {
						"0.0": {
							"vector": [0, 0, 0]
						},
						"0.1667": {
							"vector": [0, 0, -55]
						},
						"0.3333": {
							"vector": [0, 0, 0]
						}
					},
					"position": {
						"0.0": {
							"vector": [0, 0, 0]
						},
						"0.1667": {
							"vector": [8, 0, 0]
						},
						"0.3333": {
							"vector": [0, 0, 0]
						}
					}
				},
				"Rwing": {
					"rotation": {
						"0.0": {
							"vector": [0, 0, 0]
						},
						"0.1667": {
							"vector": [0, 0, 55]
						},
						"0.3333": {
							"vector": [0, 0, 0]
						}
					},
					"position": {
						"0.0": {
							"vector": [0, 0, 0]
						},
						"0.1667": {
							"vector": [-8, 0, 0]
						},
						"0.3333": {
							"vector": [0, 0, 0]
						}
					}
				}
			}
		}
	},
	"geckolib_format_version": 2
}