{
	"credit": "Made with Blockbench",
	"textures": {
		"0": "harbingerofhistory:block/pumpkin_side",
		"1": "harbingerofhistory:block/helloween_pumpkin",
		"2": "harbingerofhistory:block/black_texture",
		"particle": "harbingerofhistory:block/pumpkin_side"
	},
	"elements": [
		{
			"from": [5, 0, 5],
			"to": [11, 1, 11],
			"faces": {
				"north": {"uv": [0, 0, 6, 1], "texture": "#0"},
				"east": {"uv": [0, 0, 6, 1], "texture": "#0"},
				"south": {"uv": [0, 0, 6, 1], "texture": "#0"},
				"west": {"uv": [0, 0, 6, 1], "texture": "#0"},
				"up": {"uv": [0, 0, 6, 6], "texture": "#0"},
				"down": {"uv": [0, 0, 6, 6], "texture": "#0"}
			}
		},
		{
			"from": [11, 1, 5],
			"to": [12, 2, 11],
			"faces": {
				"north": {"uv": [0, 0, 1, 1], "texture": "#0"},
				"east": {"uv": [0, 0, 6, 1], "texture": "#0"},
				"south": {"uv": [0, 0, 1, 1], "texture": "#0"},
				"west": {"uv": [0, 0, 6, 1], "texture": "#0"},
				"up": {"uv": [0, 0, 1, 6], "texture": "#0"},
				"down": {"uv": [0, 0, 1, 6], "texture": "#0"}
			}
		},
		{
			"from": [12, 2, 5],
			"to": [13, 3, 11],
			"faces": {
				"north": {"uv": [0, 0, 1, 1], "texture": "#0"},
				"east": {"uv": [0, 0, 6, 1], "texture": "#0"},
				"south": {"uv": [0, 0, 1, 1], "texture": "#0"},
				"west": {"uv": [0, 0, 6, 1], "texture": "#0"},
				"up": {"uv": [0, 0, 1, 6], "texture": "#0"},
				"down": {"uv": [0, 0, 1, 6], "texture": "#0"}
			}
		},
		{
			"from": [12, 3, 4],
			"to": [13, 7, 12],
			"faces": {
				"north": {"uv": [0, 0, 1, 4], "texture": "#0"},
				"east": {"uv": [0, 0, 8, 4], "texture": "#0"},
				"south": {"uv": [0, 0, 1, 4], "texture": "#0"},
				"west": {"uv": [0, 0, 8, 4], "texture": "#0"},
				"up": {"uv": [0, 0, 1, 8], "texture": "#0"},
				"down": {"uv": [0, 0, 1, 8], "texture": "#0"}
			}
		},
		{
			"from": [12, 7, 3],
			"to": [13, 8, 13],
			"faces": {
				"north": {"uv": [0, 0, 1, 1], "texture": "#0"},
				"east": {"uv": [0, 0, 10, 1], "texture": "#0"},
				"south": {"uv": [0, 0, 1, 1], "texture": "#0"},
				"west": {"uv": [0, 0, 10, 1], "texture": "#0"},
				"up": {"uv": [0, 0, 1, 10], "texture": "#0"},
				"down": {"uv": [0, 0, 1, 10], "texture": "#0"}
			}
		},
		{
			"from": [5, 1, 4],
			"to": [11, 2, 5],
			"faces": {
				"north": {"uv": [0, 0, 6, 1], "texture": "#0"},
				"east": {"uv": [0, 0, 1, 1], "texture": "#0"},
				"south": {"uv": [0, 0, 6, 1], "texture": "#0"},
				"west": {"uv": [0, 0, 1, 1], "texture": "#0"},
				"up": {"uv": [0, 0, 6, 1], "texture": "#0"},
				"down": {"uv": [0, 0, 6, 1], "texture": "#0"}
			}
		},
		{
			"from": [5, 2, 3],
			"to": [11, 3, 4],
			"faces": {
				"north": {"uv": [5, 12, 11, 13], "texture": "#1"},
				"east": {"uv": [5, 6, 6, 7], "texture": "#1"},
				"south": {"uv": [0, 0, 6, 1], "texture": "#0"},
				"west": {"uv": [5, 6, 6, 7], "texture": "#1"},
				"up": {"uv": [0, 0, 6, 1], "texture": "#0"},
				"down": {"uv": [5, 12, 11, 13], "texture": "#1"}
			}
		},
		{
			"from": [4, 3, 3],
			"to": [12, 7, 4],
			"faces": {
				"north": {"uv": [4, 7, 12, 11], "texture": "#1"},
				"east": {"uv": [0, 0, 1, 4], "texture": "#0"},
				"south": {"uv": [0, 0, 8, 4], "texture": "#0"},
				"west": {"uv": [0, 0, 1, 4], "texture": "#0"},
				"up": {"uv": [0, 0, 8, 1], "texture": "#0"},
				"down": {"uv": [4, 10, 12, 11], "texture": "#1"}
			}
		},
		{
			"from": [4, 7, 3],
			"to": [12, 8, 4],
			"faces": {
				"north": {"uv": [0, 0, 8, 1], "texture": "#0"},
				"east": {"uv": [0, 0, 1, 1], "texture": "#0"},
				"south": {"uv": [0, 0, 8, 1], "texture": "#0"},
				"west": {"uv": [0, 0, 1, 1], "texture": "#0"},
				"up": {"uv": [0, 0, 8, 1], "texture": "#0"},
				"down": {"uv": [0, 0, 8, 1], "texture": "#0"}
			}
		},
		{
			"from": [7, 8, 3],
			"to": [9, 9, 4],
			"faces": {
				"north": {"uv": [0, 0, 2, 1], "texture": "#2"},
				"east": {"uv": [0, 0, 2, 1], "texture": "#2"},
				"south": {"uv": [0, 0, 2, 1], "texture": "#2"},
				"west": {"uv": [0, 0, 2, 1], "texture": "#2"},
				"up": {"uv": [0, 0, 2, 1], "texture": "#2"},
				"down": {"uv": [0, 0, 2, 1], "texture": "#2"}
			}
		},
		{
			"from": [7, 9, 3],
			"to": [9, 10, 4],
			"faces": {
				"north": {"uv": [0, 0, 2, 1], "texture": "#2"},
				"east": {"uv": [2, 1, 3, 2], "texture": "#2"},
				"south": {"uv": [0, 1, 2, 2], "texture": "#2"},
				"west": {"uv": [2, 2, 3, 3], "texture": "#2"},
				"up": {"uv": [2, 3, 0, 2], "texture": "#2"},
				"down": {"uv": [4, 0, 2, 1], "texture": "#2"}
			}
		},
		{
			"from": [7, 8, 12],
			"to": [9, 9, 13],
			"faces": {
				"north": {"uv": [0, 0, 2, 1], "texture": "#2"},
				"east": {"uv": [0, 0, 2, 1], "texture": "#2"},
				"south": {"uv": [0, 0, 2, 1], "texture": "#2"},
				"west": {"uv": [0, 0, 2, 1], "texture": "#2"},
				"up": {"uv": [0, 0, 2, 1], "texture": "#2"},
				"down": {"uv": [0, 0, 2, 1], "texture": "#2"}
			}
		},
		{
			"from": [7, 9, 12],
			"to": [9, 10, 13],
			"faces": {
				"north": {"uv": [0, 0, 1, 1], "texture": "#2"},
				"east": {"uv": [0, 0, 1, 1], "texture": "#2"},
				"south": {"uv": [0, 0, 1, 1], "texture": "#2"},
				"west": {"uv": [0, 0, 1, 1], "texture": "#2"},
				"up": {"uv": [0, 0, 1, 1], "texture": "#2"},
				"down": {"uv": [0, 0, 1, 1], "texture": "#2"}
			}
		},
		{
			"from": [7, 10, 11],
			"to": [9, 11, 12],
			"faces": {
				"north": {"uv": [0, 0, 1, 1], "texture": "#2"},
				"east": {"uv": [0, 0, 1, 1], "texture": "#2"},
				"south": {"uv": [0, 0, 1, 1], "texture": "#2"},
				"west": {"uv": [0, 0, 1, 1], "texture": "#2"},
				"up": {"uv": [0, 0, 1, 1], "texture": "#2"},
				"down": {"uv": [0, 0, 1, 1], "texture": "#2"}
			}
		},
		{
			"from": [7, 11, 10],
			"to": [9, 12, 11],
			"faces": {
				"north": {"uv": [0, 0, 1, 1], "texture": "#2"},
				"east": {"uv": [0, 0, 1, 1], "texture": "#2"},
				"south": {"uv": [0, 0, 1, 1], "texture": "#2"},
				"west": {"uv": [0, 0, 1, 1], "texture": "#2"},
				"up": {"uv": [0, 0, 1, 1], "texture": "#2"},
				"down": {"uv": [0, 0, 1, 1], "texture": "#2"}
			}
		},
		{
			"from": [7, 12, 6],
			"to": [9, 13, 10],
			"faces": {
				"north": {"uv": [0, 0, 4, 1], "texture": "#2"},
				"east": {"uv": [0, 0, 4, 1], "texture": "#2"},
				"south": {"uv": [0, 0, 4, 1], "texture": "#2"},
				"west": {"uv": [0, 0, 4, 1], "texture": "#2"},
				"up": {"uv": [0, 0, 4, 1], "texture": "#2"},
				"down": {"uv": [0, 0, 4, 1], "texture": "#2"}
			}
		},
		{
			"from": [7, 10, 4],
			"to": [9, 11, 5],
			"faces": {
				"north": {"uv": [0, 0, 1, 1], "texture": "#2"},
				"east": {"uv": [0, 0, 1, 1], "texture": "#2"},
				"south": {"uv": [0, 0, 1, 1], "texture": "#2"},
				"west": {"uv": [0, 0, 1, 1], "texture": "#2"},
				"up": {"uv": [0, 0, 1, 1], "texture": "#2"},
				"down": {"uv": [0, 0, 1, 1], "texture": "#2"}
			}
		},
		{
			"from": [7, 11, 5],
			"to": [9, 12, 6],
			"faces": {
				"north": {"uv": [0, 0, 1, 1], "texture": "#2"},
				"east": {"uv": [0, 0, 1, 1], "texture": "#2"},
				"south": {"uv": [0, 0, 1, 1], "texture": "#2"},
				"west": {"uv": [0, 0, 1, 1], "texture": "#2"},
				"up": {"uv": [0, 0, 1, 1], "texture": "#2"},
				"down": {"uv": [0, 0, 1, 1], "texture": "#2"}
			}
		},
		{
			"from": [4, 1, 5],
			"to": [5, 2, 11],
			"faces": {
				"north": {"uv": [0, 0, 1, 1], "texture": "#0"},
				"east": {"uv": [0, 0, 6, 1], "texture": "#0"},
				"south": {"uv": [0, 0, 1, 1], "texture": "#0"},
				"west": {"uv": [0, 0, 6, 1], "texture": "#0"},
				"up": {"uv": [0, 0, 1, 6], "texture": "#0"},
				"down": {"uv": [0, 0, 1, 6], "texture": "#0"}
			}
		},
		{
			"from": [3, 2, 5],
			"to": [4, 3, 11],
			"faces": {
				"north": {"uv": [0, 0, 1, 1], "texture": "#0"},
				"east": {"uv": [0, 0, 6, 1], "texture": "#0"},
				"south": {"uv": [0, 0, 1, 1], "texture": "#0"},
				"west": {"uv": [0, 0, 6, 1], "texture": "#0"},
				"up": {"uv": [0, 0, 1, 6], "texture": "#0"},
				"down": {"uv": [0, 0, 1, 6], "texture": "#0"}
			}
		},
		{
			"from": [3, 3, 4],
			"to": [4, 7, 12],
			"faces": {
				"north": {"uv": [0, 0, 1, 4], "texture": "#0"},
				"east": {"uv": [0, 0, 8, 4], "texture": "#0"},
				"south": {"uv": [0, 0, 1, 4], "texture": "#0"},
				"west": {"uv": [0, 0, 8, 4], "texture": "#0"},
				"up": {"uv": [0, 0, 1, 8], "texture": "#0"},
				"down": {"uv": [0, 0, 1, 8], "texture": "#0"}
			}
		},
		{
			"from": [3, 7, 3],
			"to": [4, 8, 13],
			"faces": {
				"north": {"uv": [0, 0, 1, 1], "texture": "#0"},
				"east": {"uv": [0, 0, 10, 1], "texture": "#0"},
				"south": {"uv": [0, 0, 1, 1], "texture": "#0"},
				"west": {"uv": [0, 0, 10, 1], "texture": "#0"},
				"up": {"uv": [0, 0, 1, 10], "texture": "#0"},
				"down": {"uv": [0, 0, 1, 10], "texture": "#0"}
			}
		},
		{
			"from": [4, 2, 4],
			"to": [5, 3, 5],
			"faces": {
				"north": {"uv": [0, 0, 1, 1], "texture": "#0"},
				"east": {"uv": [0, 0, 1, 1], "texture": "#0"},
				"south": {"uv": [0, 0, 1, 1], "texture": "#0"},
				"west": {"uv": [0, 0, 1, 1], "texture": "#0"},
				"up": {"uv": [0, 0, 1, 1], "texture": "#0"},
				"down": {"uv": [0, 0, 1, 1], "texture": "#0"}
			}
		},
		{
			"from": [4, 2, 11],
			"to": [5, 3, 12],
			"faces": {
				"north": {"uv": [0, 0, 1, 1], "texture": "#0"},
				"east": {"uv": [0, 0, 1, 1], "texture": "#0"},
				"south": {"uv": [0, 0, 1, 1], "texture": "#0"},
				"west": {"uv": [0, 0, 1, 1], "texture": "#0"},
				"up": {"uv": [0, 0, 1, 1], "texture": "#0"},
				"down": {"uv": [0, 0, 1, 1], "texture": "#0"}
			}
		},
		{
			"from": [11, 2, 11],
			"to": [12, 3, 12],
			"faces": {
				"north": {"uv": [0, 0, 1, 1], "texture": "#0"},
				"east": {"uv": [0, 0, 1, 1], "texture": "#0"},
				"south": {"uv": [0, 0, 1, 1], "texture": "#0"},
				"west": {"uv": [0, 0, 1, 1], "texture": "#0"},
				"up": {"uv": [0, 0, 1, 1], "texture": "#0"},
				"down": {"uv": [0, 0, 1, 1], "texture": "#0"}
			}
		},
		{
			"from": [11, 2, 4],
			"to": [12, 3, 5],
			"faces": {
				"north": {"uv": [0, 0, 1, 1], "texture": "#0"},
				"east": {"uv": [0, 0, 1, 1], "texture": "#0"},
				"south": {"uv": [0, 0, 1, 1], "texture": "#0"},
				"west": {"uv": [0, 0, 1, 1], "texture": "#0"},
				"up": {"uv": [0, 0, 1, 1], "texture": "#0"},
				"down": {"uv": [0, 0, 1, 1], "texture": "#0"}
			}
		},
		{
			"from": [5, 1, 11],
			"to": [11, 2, 12],
			"faces": {
				"north": {"uv": [0, 0, 6, 1], "texture": "#0"},
				"east": {"uv": [0, 0, 1, 1], "texture": "#0"},
				"south": {"uv": [0, 0, 6, 1], "texture": "#0"},
				"west": {"uv": [0, 0, 1, 1], "texture": "#0"},
				"up": {"uv": [0, 0, 6, 1], "texture": "#0"},
				"down": {"uv": [0, 0, 6, 1], "texture": "#0"}
			}
		},
		{
			"from": [5, 2, 12],
			"to": [11, 3, 13],
			"faces": {
				"north": {"uv": [0, 0, 6, 1], "texture": "#0"},
				"east": {"uv": [0, 0, 1, 1], "texture": "#0"},
				"south": {"uv": [0, 0, 6, 1], "texture": "#0"},
				"west": {"uv": [0, 0, 1, 1], "texture": "#0"},
				"up": {"uv": [0, 0, 6, 1], "texture": "#0"},
				"down": {"uv": [0, 0, 6, 1], "texture": "#0"}
			}
		},
		{
			"from": [4, 3, 12],
			"to": [12, 7, 13],
			"faces": {
				"north": {"uv": [0, 0, 8, 4], "texture": "#0"},
				"east": {"uv": [0, 0, 1, 4], "texture": "#0"},
				"south": {"uv": [0, 0, 8, 4], "texture": "#0"},
				"west": {"uv": [0, 0, 1, 4], "texture": "#0"},
				"up": {"uv": [0, 0, 8, 1], "texture": "#0"},
				"down": {"uv": [0, 0, 8, 1], "texture": "#0"}
			}
		},
		{
			"from": [4, 7, 12],
			"to": [12, 8, 13],
			"faces": {
				"north": {"uv": [0, 0, 8, 1], "texture": "#0"},
				"east": {"uv": [0, 0, 1, 1], "texture": "#0"},
				"south": {"uv": [0, 0, 8, 1], "texture": "#0"},
				"west": {"uv": [0, 0, 1, 1], "texture": "#0"},
				"up": {"uv": [0, 0, 8, 1], "texture": "#0"},
				"down": {"uv": [0, 0, 8, 1], "texture": "#0"}
			}
		}
	],
	"display": {
		"thirdperson_righthand": {
			"rotation": [77.75, 0, 0],
			"translation": [0, -1.75, -1.25],
			"scale": [0.55, 0.54, 0.54]
		},
		"thirdperson_lefthand": {
			"rotation": [66.75, 0, 0],
			"translation": [0, -1.75, -1.75],
			"scale": [0.57, 0.57, 0.57]
		},
		"ground": {
			"scale": [0.57, 0.57, 0.56]
		},
		"gui": {
			"rotation": [-180, 36.75, -180]
		},
		"head": {
			"translation": [0, 3.25, 0],
			"scale": [1.67, 1.66, 1.64]
		},
		"fixed": {
			"rotation": [0, -38, 0]
		}
	}
}